.bumpversion.cfg
.editorconfig
.gitignore
MANIFEST.in
Makefile
requirements.txt
setup.py
docs/README.rst
docs/TODO.rst
docs/conf.py
docs/docs.cfg
docs/index.rst
docs/localization.rst
src/sphinx_paw/__init__.py
src/sphinx_paw/configurable.py
src/sphinx_paw/constants.py
src/sphinx_paw/exceptions.py
src/sphinx_paw/main_params.py
src/sphinx_paw/rewritable.py
src/sphinx_paw/setup_command.py
src/sphinx_paw/sphinx_wrapper.py
src/sphinx_paw/translation.py
src/sphinx_paw/utils.py
src/sphinx_paw.egg-info/PKG-INFO
src/sphinx_paw.egg-info/SOURCES.txt
src/sphinx_paw.egg-info/dependency_links.txt
src/sphinx_paw.egg-info/entry_points.txt
src/sphinx_paw.egg-info/not-zip-safe
src/sphinx_paw.egg-info/top_level.txt
src/sphinx_paw/__pycache__/__init__.cpython-36.pyc
src/sphinx_paw/__pycache__/configurable.cpython-36.pyc
src/sphinx_paw/__pycache__/constants.cpython-36.pyc
src/sphinx_paw/__pycache__/exceptions.cpython-36.pyc
src/sphinx_paw/__pycache__/main_params.cpython-36.pyc
src/sphinx_paw/__pycache__/rewritable.cpython-36.pyc
src/sphinx_paw/__pycache__/translation.cpython-36.pyc
src/sphinx_paw/__pycache__/utils.cpython-36.pyc
src/sphinx_paw/builders/__init__.py
src/sphinx_paw/builders/confluence.py
src/sphinx_paw/builders/htmldir.py
src/sphinx_paw/builders/latexpdf.py
src/sphinx_paw/builders/__pycache__/__init__.cpython-36.pyc
src/sphinx_paw/builders/__pycache__/confluence.cpython-36.pyc
src/sphinx_paw/builders/__pycache__/htmldir.cpython-36.pyc
src/sphinx_paw/builders/__pycache__/latexpdf.cpython-36.pyc
src/sphinx_paw/builders/constants/__init__.py
src/sphinx_paw/builders/constants/latexpdf.py
src/sphinx_paw/builders/constants/__pycache__/__init__.cpython-36.pyc
src/sphinx_paw/builders/constants/__pycache__/latexpdf.cpython-36.pyc
src/sphinx_paw/cmdline/__init__.py
src/sphinx_paw/cmdline/init.py
src/sphinx_paw/defaults/atendofbody.tex
src/sphinx_paw/defaults/conf.py
src/sphinx_paw/defaults/preamble.tex
src/sphinx_paw/extensions/__init__.py
src/sphinx_paw/extensions/autodoc.py
src/sphinx_paw/extensions/__pycache__/__init__.cpython-36.pyc
src/sphinx_paw/locales/sphinx_paw.pot
src/sphinx_paw/locales/ru_RU/LC_MESSAGES/sphinx_paw.mo
src/sphinx_paw/locales/ru_RU/LC_MESSAGES/sphinx_paw.po
